teedoc_plugin_assets/__init__.py
teedoc_plugin_assets-1.1.2.dist-info/LICENSE
teedoc_plugin_assets-1.1.2.dist-info/METADATA
teedoc_plugin_assets-1.1.2.dist-info/WHEEL
teedoc_plugin_assets-1.1.2.dist-info/top_level.txt
teedoc_plugin_assets-1.1.2.dist-info/RECORD
