Metadata-Version: 2.1
Name: teedoc-plugin-assets
Version: 1.1.2
Summary: assets plugin for teedoc to add css and js assets to pages or other custom items to pages
Home-page: https://github.com/teedoc/teedoc
Author: Neucrack
Author-email: CZD666666@gmail.com
License: MIT
Keywords: assets css js teedoc plugin
Platform: UNKNOWN
Classifier: Intended Audience :: Developers
Classifier: License :: OSI Approved :: MIT License
Classifier: Programming Language :: Python :: 3
